cutepywin/__init__.py
cutepywin/cutepy.py
cutepywin-0.0.4.dist-info/METADATA
cutepywin-0.0.4.dist-info/WHEEL
cutepywin-0.0.4.dist-info/top_level.txt
cutepywin-0.0.4.dist-info/RECORD
