Metadata-Version: 2.1
Name: cutepywin
Version: 0.0.4
Summary: A helpfull python package!
Author: 0x0060
Author-email: <ren@0x0060.dev>
Keywords: python,python system Detection,python hex,python rgb,python hex,python loader,rich python,python rich,cutepy
